satlas2/__init__.py
satlas2/core.py
satlas2/interface.py
satlas2/models/__init__.py
satlas2/models/hfsModel.py
satlas2/models/models.py
satlas2/overwrite.py
satlas2/plotting.py
satlas2/utilities.py
satlas2-0.2.8.dist-info/LICENSE
satlas2-0.2.8.dist-info/METADATA
satlas2-0.2.8.dist-info/WHEEL
satlas2-0.2.8.dist-info/RECORD
