Metadata-Version: 2.3
Name: satlas2
Version: 0.2.8
Summary: Fitting package aimed at laser spectroscopy
License: MIT
Keywords: physics,hyperfine structure,fitting
Author: Ruben de Groote,
Author-email: ruben.degroote@kuleuven.be
Requires-Python: >=3.10.0,<4.0.0
Classifier: Development Status :: 4 - Beta
Classifier: Intended Audience :: Science/Research
Classifier: License :: OSI Approved :: MIT License
Classifier: Operating System :: Microsoft :: Windows
Classifier: Programming Language :: Python :: 3
Classifier: Programming Language :: Python :: 3.10
Classifier: Programming Language :: Python :: 3.11
Classifier: Programming Language :: Python :: 3.12
Classifier: Programming Language :: Python :: 3.13
Classifier: Programming Language :: Python :: 3 :: Only
Classifier: Topic :: Scientific/Engineering :: Physics
Requires-Dist: emcee (>=3.1.4,<4.0.0)
Requires-Dist: h5py (>=3.10.0,<4.0.0)
Requires-Dist: lmfit (>=1.2.2,<2.0.0)
Requires-Dist: matplotlib (>=3.8.0,<4.0.0)
Requires-Dist: numdifftools (>=0.9.41,<0.10.0)
Requires-Dist: numpy (>=2.1.3,<3.0.0)
Requires-Dist: pandas (>=2.1.1,<3.0.0)
Requires-Dist: scipy (>=1.11.3,<2.0.0)
Requires-Dist: sympy (>=1.12,<2.0)
Requires-Dist: tqdm (>=4.66.1,<5.0.0)
Requires-Dist: uncertainties (>=3.1.7,<4.0.0)
